LICENSE
mmpost/__init__.py
mmpost/mmpost.py
mmpost-0.0.6.dist-info/entry_points.txt
mmpost-0.0.6.dist-info/LICENSE
mmpost-0.0.6.dist-info/WHEEL
mmpost-0.0.6.dist-info/METADATA
mmpost-0.0.6.dist-info/RECORD
