Metadata-Version: 2.1
Name: mmpost
Version: 0.0.6
Summary: Mattermost post message
Home-page: https://github.com/frbor/mmpost
License: ISC
Keywords: mattermost,cli
Author: Fredrik Borg
Author-email: fredrik.borg@gmail.com
Requires-Python: >=3.6.1,<4.0.0
Classifier: License :: OSI Approved
Classifier: Programming Language :: Python :: 3
Classifier: Programming Language :: Python :: 3.7
Classifier: Programming Language :: Python :: 3.8
Classifier: Programming Language :: Python :: 3.9
Requires-Dist: caep
Requires-Dist: mattermostdriver
Project-URL: Repository, https://github.com/frbor/mmpost
